mypackage/__init__.py
mypackage/mypackage.py
afraz_pack-0.2.dist-info/LICENSE
afraz_pack-0.2.dist-info/METADATA
afraz_pack-0.2.dist-info/WHEEL
afraz_pack-0.2.dist-info/top_level.txt
afraz_pack-0.2.dist-info/RECORD
